getent/__init__.py
getent/constants.py
getent/headers.py
getent/libc.py
getent2-0.2.dist-info/METADATA
getent2-0.2.dist-info/WHEEL
getent2-0.2.dist-info/RECORD
