Metadata-Version: 2.1
Name: getent2
Version: 0.2
Summary: Python interface to the POSIX getent family of commands
License: MIT
Author: Wijnand Modderman-Lenstra
Author-email: maze@pyth0n.org
Requires-Python: >=3.10,<4.0
Classifier: License :: OSI Approved :: MIT License
Classifier: Programming Language :: Python :: 3
Classifier: Programming Language :: Python :: 3.10
Classifier: Programming Language :: Python :: 3.11
Classifier: Programming Language :: Python :: 3.12
